LICENSE.txt
MANIFEST.in
README.md
setup.py
umar_python_tools.egg-info/PKG-INFO
umar_python_tools.egg-info/SOURCES.txt
umar_python_tools.egg-info/dependency_links.txt
umar_python_tools.egg-info/top_level.txt
umarpythontools/__init__.py
umarpythontools/math_tools.py
umarpythontools/text_tools.py